demo_workflow_pypi/__init__.py
demo_workflow_pypi/main.py
demo_workflow_pypi-0.5.2.dist-info/METADATA
demo_workflow_pypi-0.5.2.dist-info/WHEEL
demo_workflow_pypi-0.5.2.dist-info/RECORD
